<?xml version="1.0" encoding="utf-8" ?>
<dwsync>
<file name="customer_site_options.php" server="ftp.2-all.com/www/2-all.com/2-all/webapps/" local="129820136104190000" remote="129822577800000000" />
<file name="customers.php" server="ftp.2-all.com/www/2-all.com/2-all/webapps/" local="129820136104150000" remote="129822577800000000" />
<file name="engines_all.php" server="ftp.2-all.com/www/2-all.com/2-all/webapps/" local="129820136104230000" remote="129822577800000000" />
<file name="engines_ru.php" server="ftp.2-all.com/www/2-all.com/2-all/webapps/" local="129820136104270000" remote="129822577800000000" />
<file name="index.html" server="ftp.2-all.com/www/2-all.com/2-all/webapps/" local="129820136104310000" remote="129822577800000000" />
<file name="options_beyond_sides.php" server="ftp.2-all.com/www/2-all.com/2-all/webapps/" local="129820136104350000" remote="129822577800000000" />
<file name="site_options.php" server="ftp.2-all.com/www/2-all.com/2-all/webapps/" local="129820136104430000" remote="129822577800000000" />
<file name="site_options_partial.php" server="ftp.2-all.com/www/2-all.com/2-all/webapps/" local="129820136104460000" remote="129822577800000000" />
<file name="site_options_types.php" server="ftp.2-all.com/www/2-all.com/2-all/webapps/" local="129820136104500000" remote="129822577800000000" />
<file name="site_types.php" server="ftp.2-all.com/www/2-all.com/2-all/webapps/" local="129820136104540000" remote="129822577800000000" />
<file name="customer_site_options.php" server="ftp.2-all.com" local="129811414225748000" remote="129814512600000000" />
<file name="precustomers.php" server="ftp.2-all.com/www/2-all.com/2-all/webapps/" local="129820136104390000" remote="129822577800000000" />
</dwsync>